{
  "formatted_snapshots": [
    {
      "code": "#include <iostream>\nusing namespace std;\n\nint main() {\n    int number;\n    cout << \"Enter an Number: \";\n    cin >> number;\n\n    double result = sqrt(number);\n\n    cout << fixed << setprecision\n\n\n    return 0;\n}",
      "learner_id": "68122d4c2c1c50f5cb914ddd",
      "submission_id": "681769e3e7010ff37c986b2e",
      "timestamp": ""
    },
    {
      "code": "#include <iostream>\n#include <cmath>\n#include <iomanip>\nusing namespace std;\n\nint main() {\n    int num;\n    cout << \"Enter an Number: \";\n    cin >> num;\n\n    double result = sqrt(num);\n\n    cout << fixed << setprecision(2);\n    cout << \"Square Root: \" << result << endl;\n\n\n    return 0;\n}",
      "learner_id": "68122d4c2c1c50f5cb914ddd",
      "submission_id": "68176ad0e7010ff37c986b5f",
      "timestamp": ""
    },
    {
      "code": "#include <iostream>\nusing namespace std;\n\nint main() {\n    int num;\n    cout << \"Enter an Number: \";\n    cin >> num;\n\n    double result = sqrt(num);\n\n    cout << fixed << setprecision(2);\n    cout << \"Square Root: \" << result << endl;\n\n\n    return 0;\n}",
      "learner_id": "68122d4c2c1c50f5cb914ddd",
      "submission_id": "68176a8c7755350287ae577c",
      "timestamp": ""
    },
    {
      "code": "#include <iostream>\nusing namespace std;\n\nint main() {\n    int number;\n    cout << \"Enter an Number: \";\n    cin >> number;\n\n    double result = sqrt (number);\n\n    cout << fixed << setprecision(2);\n    cout << \"Square Root: \" << result << endl;\n\n\n    return 0;\n}",
      "learner_id": "68122d4c2c1c50f5cb914ddd",
      "submission_id": "68176a667755350287ae576e",
      "timestamp": ""
    },
    {
      "code": "#include <iostream>\nusing namespace std;\n\nint main() {\n    int number;\n    cout << \"Enter an Number: \";\n    cin >> number;\n\n    double result = sqrt(number);\n\n    cout << fixed << setprecision(2);\n    cout << \"Square Root: \" << result << endl;\n\n\n    return 0;\n}",
      "learner_id": "68122d4c2c1c50f5cb914ddd",
      "submission_id": "68176a0be7010ff37c986b50",
      "timestamp": ""
    },
    {
      "code": "#include <iostream>\nusing namespace std;\n\nint main() {\n    int number;\n    cout << \"Enter an Number: \";\n    cin >> number;\n\n    double result = sqrt(number);\n\n    cout << fixed << setprecision(2);\n    cout << \"Square Root: \" << result\n\n\n    return 0;\n}",
      "learner_id": "68122d4c2c1c50f5cb914ddd",
      "submission_id": "68176a08e7010ff37c986b4c",
      "timestamp": ""
    },
    {
      "code": "#include <iostream>\nusing namespace std;\n\nint main() {\n    int number;\n    cout << \"Enter an Number: \";\n    cin >> number;\n\n    double result = sqrt(number);\n\n    cout << fixed << setprecision(2);\n    cout << \"Square Root: \"\n\n\n    return 0;\n}",
      "learner_id": "68122d4c2c1c50f5cb914ddd",
      "submission_id": "68176a03e7010ff37c986b48",
      "timestamp": ""
    },
    {
      "code": "#include <iostream>\nusing namespace std;\n\nint main() {\n    int number;\n    cout << \"Enter an Number: \";\n    cin >> number;\n\n    double result = sqrt(number);\n\n    cout << fixed << setprecision(2);\n    cout << \"Square Root\"\n\n\n    return 0;\n}",
      "learner_id": "68122d4c2c1c50f5cb914ddd",
      "submission_id": "68176a00e7010ff37c986b44",
      "timestamp": ""
    },
    {
      "code": "#include <iostream>\nusing namespace std;\n\nint main() {\n    int number;\n    cout << \"Enter an Number: \";\n    cin >> number;\n\n    double result = sqrt(number);\n\n    cout << fixed << setprecision(2);\n    cout << sq\n\n\n    return 0;\n}",
      "learner_id": "68122d4c2c1c50f5cb914ddd",
      "submission_id": "681769fae7010ff37c986b40",
      "timestamp": ""
    },
    {
      "code": "#include <iostream>\nusing namespace std;\n\nint main() {\n    int number;\n    cout << \"Enter an Number: \";\n    cin >> number;\n\n    double result = sqrt(number);\n\n    cout << fixed << setprecision(2);\n    \n\n\n    return 0;\n}",
      "learner_id": "68122d4c2c1c50f5cb914ddd",
      "submission_id": "681769f2e7010ff37c986b3a",
      "timestamp": ""
    },
    {
      "code": "#include <iostream>\nusing namespace std;\n\nint main() {\n    int number;\n    cout << \"Enter an Number: \";\n    cin >> number;\n\n    double result = sqrt(number);\n\n    cout << fixed << setprecision(2);\n\n\n    return 0;\n}",
      "learner_id": "68122d4c2c1c50f5cb914ddd",
      "submission_id": "681769ebe7010ff37c986b36",
      "timestamp": ""
    },
    {
      "code": "#include <iostream>\nusing namespace std;\n\nint main() {\n    int number;\n    cout << \"Enter an Number: \";\n    cin >> number;\n\n    double result = sqrt(number);\n\n    cout << fixed << setprecision(2)\n\n\n    return 0;\n}",
      "learner_id": "68122d4c2c1c50f5cb914ddd",
      "submission_id": "681769e7e7010ff37c986b32",
      "timestamp": ""
    },
    {
      "code": "#include <iostream>\nusing namespace std;\n\nint main() {\n    \n    return 0;\n}",
      "learner_id": "68122d4c2c1c50f5cb914ddd",
      "submission_id": "6817695f7755350287ae5730",
      "timestamp": ""
    },
    {
      "code": "#include <iostream>\nusing namespace std;\n\nint main() {\n    int number;\n    cout << \"Enter an Number: \";\n    cin >> number;\n\n    double result = sqrt(number);\n\n    cout <<\n\n\n    return 0;\n}",
      "learner_id": "68122d4c2c1c50f5cb914ddd",
      "submission_id": "681769d3e7010ff37c986b27",
      "timestamp": ""
    },
    {
      "code": "#include <iostream>\nusing namespace std;\n\nint main() {\n    int number;\n    cout << \"Enter an Number: \";\n    cin >> number;\n\n    double result = sqrt(number);\n\n\n    return 0;\n}",
      "learner_id": "68122d4c2c1c50f5cb914ddd",
      "submission_id": "681769cd7755350287ae5758",
      "timestamp": ""
    },
    {
      "code": "#include <iostream>\nusing namespace std;\n\nint main() {\n    int number;\n    cout << \"Enter an Number: \";\n    cin >> number;\n\n    double result = sqrt \n\n\n    return 0;\n}",
      "learner_id": "68122d4c2c1c50f5cb914ddd",
      "submission_id": "681769c87755350287ae5754",
      "timestamp": ""
    },
    {
      "code": "#include <iostream>\nusing namespace std;\n\nint main() {\n    int number;\n    cout << \"Enter an Number: \";\n    cin >> number;\n\n    double result = \n\n\n    return 0;\n}",
      "learner_id": "68122d4c2c1c50f5cb914ddd",
      "submission_id": "681769c37755350287ae574f",
      "timestamp": ""
    },
    {
      "code": "#include <iostream>\nusing namespace std;\n\nint main() {\n    int number;\n    cout << \"Enter an Number: \";\n    cin >> number;\n\n    double sqrt \n\n\n    return 0;\n}",
      "learner_id": "68122d4c2c1c50f5cb914ddd",
      "submission_id": "681769b77755350287ae574b",
      "timestamp": ""
    },
    {
      "code": "#include <iostream>\nusing namespace std;\n\nint main() {\n    int number;\n    cout << \"Enter an Number: \";\n    cin >> number;\n\n    d\n\n\n    return 0;\n}",
      "learner_id": "68122d4c2c1c50f5cb914ddd",
      "submission_id": "681769b27755350287ae5747",
      "timestamp": ""
    },
    {
      "code": "#include <iostream>\nusing namespace std;\n\nint main() {\n    int number;\n    cout << \"Enter an Number: \";\n    cin >> number;\n\n\n    \n    return 0;\n}",
      "learner_id": "68122d4c2c1c50f5cb914ddd",
      "submission_id": "681769a77755350287ae573f",
      "timestamp": ""
    },
    {
      "code": "#include <iostream>\nusing namespace std;\n\nint main() {\n    int number;\n    cout << \"Enter an Number: \";\n    cin >> number;\n    return 0;\n}",
      "learner_id": "68122d4c2c1c50f5cb914ddd",
      "submission_id": "681769a17755350287ae573a",
      "timestamp": ""
    },
    {
      "code": "#include <iostream>\nusing namespace std;\n\nint main() {\n    int number;\n    cout << \"Enter an Number: \";\n    return 0;\n}",
      "learner_id": "68122d4c2c1c50f5cb914ddd",
      "submission_id": "68176999e7010ff37c986b23",
      "timestamp": ""
    },
    {
      "code": "#include <iostream>\nusing namespace std;\n\nint main() {\n    int number;\n    cout << \"Enter an Number:\";\n    return 0;\n}",
      "learner_id": "68122d4c2c1c50f5cb914ddd",
      "submission_id": "68176994e7010ff37c986b1f",
      "timestamp": ""
    },
    {
      "code": "#include <iostream>\nusing namespace std;\n\nint main() {\n    int number;\n    return 0;\n}",
      "learner_id": "68122d4c2c1c50f5cb914ddd",
      "submission_id": "6817697ee7010ff37c986b1b",
      "timestamp": ""
    }
  ],
  "sequentialSimilarities": [
    {
      "codebert_score": 68,
      "from_index": 0,
      "learner_id": "68122d4c2c1c50f5cb914ddd",
      "similarity": 68,
      "to_index": 1
    },
    {
      "codebert_score": 77,
      "from_index": 1,
      "learner_id": "68122d4c2c1c50f5cb914ddd",
      "similarity": 77,
      "to_index": 2
    },
    {
      "codebert_score": 91,
      "from_index": 2,
      "learner_id": "68122d4c2c1c50f5cb914ddd",
      "similarity": 91,
      "to_index": 3
    },
    {
      "codebert_score": 96,
      "from_index": 3,
      "learner_id": "68122d4c2c1c50f5cb914ddd",
      "similarity": 96,
      "to_index": 4
    },
    {
      "codebert_score": 85,
      "from_index": 4,
      "learner_id": "68122d4c2c1c50f5cb914ddd",
      "similarity": 85,
      "to_index": 5
    },
    {
      "codebert_score": 87,
      "from_index": 5,
      "learner_id": "68122d4c2c1c50f5cb914ddd",
      "similarity": 87,
      "to_index": 6
    },
    {
      "codebert_score": 90,
      "from_index": 6,
      "learner_id": "68122d4c2c1c50f5cb914ddd",
      "similarity": 90,
      "to_index": 7
    },
    {
      "codebert_score": 85,
      "from_index": 7,
      "learner_id": "68122d4c2c1c50f5cb914ddd",
      "similarity": 85,
      "to_index": 8
    },
    {
      "codebert_score": 87,
      "from_index": 8,
      "learner_id": "68122d4c2c1c50f5cb914ddd",
      "similarity": 87,
      "to_index": 9
    },
    {
      "codebert_score": 100,
      "from_index": 9,
      "learner_id": "68122d4c2c1c50f5cb914ddd",
      "similarity": 100,
      "to_index": 10
    },
    {
      "codebert_score": 88,
      "from_index": 10,
      "learner_id": "68122d4c2c1c50f5cb914ddd",
      "similarity": 88,
      "to_index": 11
    },
    {
      "codebert_score": 58,
      "from_index": 11,
      "learner_id": "68122d4c2c1c50f5cb914ddd",
      "similarity": 58,
      "to_index": 12
    },
    {
      "codebert_score": 61,
      "from_index": 12,
      "learner_id": "68122d4c2c1c50f5cb914ddd",
      "similarity": 61,
      "to_index": 13
    },
    {
      "codebert_score": 84,
      "from_index": 13,
      "learner_id": "68122d4c2c1c50f5cb914ddd",
      "similarity": 84,
      "to_index": 14
    },
    {
      "codebert_score": 75,
      "from_index": 14,
      "learner_id": "68122d4c2c1c50f5cb914ddd",
      "similarity": 75,
      "to_index": 15
    },
    {
      "codebert_score": 84,
      "from_index": 15,
      "learner_id": "68122d4c2c1c50f5cb914ddd",
      "similarity": 84,
      "to_index": 16
    },
    {
      "codebert_score": 84,
      "from_index": 16,
      "learner_id": "68122d4c2c1c50f5cb914ddd",
      "similarity": 84,
      "to_index": 17
    },
    {
      "codebert_score": 82,
      "from_index": 17,
      "learner_id": "68122d4c2c1c50f5cb914ddd",
      "similarity": 82,
      "to_index": 18
    },
    {
      "codebert_score": 83,
      "from_index": 18,
      "learner_id": "68122d4c2c1c50f5cb914ddd",
      "similarity": 83,
      "to_index": 19
    },
    {
      "codebert_score": 99,
      "from_index": 19,
      "learner_id": "68122d4c2c1c50f5cb914ddd",
      "similarity": 99,
      "to_index": 20
    },
    {
      "codebert_score": 81,
      "from_index": 20,
      "learner_id": "68122d4c2c1c50f5cb914ddd",
      "similarity": 81,
      "to_index": 21
    },
    {
      "codebert_score": 82,
      "from_index": 21,
      "learner_id": "68122d4c2c1c50f5cb914ddd",
      "similarity": 82,
      "to_index": 22
    },
    {
      "codebert_score": 73,
      "from_index": 22,
      "learner_id": "68122d4c2c1c50f5cb914ddd",
      "similarity": 73,
      "to_index": 23
    }
  ],
  "snapshots": [
    {
      "__v": 0,
      "_id": "681769e3e7010ff37c986b2e",
      "code": "#include <iostream>\nusing namespace std;\n\nint main() {\n    int number;\n    cout << \"Enter an Number: \";\n    cin >> number;\n\n    double result = sqrt(number);\n\n    cout << fixed << setprecision\n\n\n    return 0;\n}",
      "learner_id": "68122d4c2c1c50f5cb914ddd",
      "problemId": "perfectly-rooted-5136456806",
      "roomId": "comp-Dx7fgmm4GB",
      "submissionId": "submission-1746364899331",
      "timestamp": "Sun, 04 May 2025 13:21:39 GMT",
      "version": 13
    },
    {
      "__v": 0,
      "_id": "68176ad0e7010ff37c986b5f",
      "code": "#include <iostream>\n#include <cmath>\n#include <iomanip>\nusing namespace std;\n\nint main() {\n    int num;\n    cout << \"Enter an Number: \";\n    cin >> num;\n\n    double result = sqrt(num);\n\n    cout << fixed << setprecision(2);\n    cout << \"Square Root: \" << result << endl;\n\n\n    return 0;\n}",
      "learner_id": "68122d4c2c1c50f5cb914ddd",
      "problemId": "perfectly-rooted-5136456806",
      "roomId": "comp-Dx7fgmm4GB",
      "submissionId": "submission-1746365136215",
      "timestamp": "Sun, 04 May 2025 13:25:36 GMT",
      "version": 24
    },
    {
      "__v": 0,
      "_id": "68176a8c7755350287ae577c",
      "code": "#include <iostream>\nusing namespace std;\n\nint main() {\n    int num;\n    cout << \"Enter an Number: \";\n    cin >> num;\n\n    double result = sqrt(num);\n\n    cout << fixed << setprecision(2);\n    cout << \"Square Root: \" << result << endl;\n\n\n    return 0;\n}",
      "learner_id": "68122d4c2c1c50f5cb914ddd",
      "problemId": "perfectly-rooted-5136456806",
      "roomId": "comp-Dx7fgmm4GB",
      "submissionId": "submission-1746365068829",
      "timestamp": "Sun, 04 May 2025 13:24:28 GMT",
      "version": 23
    },
    {
      "__v": 0,
      "_id": "68176a667755350287ae576e",
      "code": "#include <iostream>\nusing namespace std;\n\nint main() {\n    int number;\n    cout << \"Enter an Number: \";\n    cin >> number;\n\n    double result = sqrt (number);\n\n    cout << fixed << setprecision(2);\n    cout << \"Square Root: \" << result << endl;\n\n\n    return 0;\n}",
      "learner_id": "68122d4c2c1c50f5cb914ddd",
      "problemId": "perfectly-rooted-5136456806",
      "roomId": "comp-Dx7fgmm4GB",
      "submissionId": "submission-1746365030515",
      "timestamp": "Sun, 04 May 2025 13:23:50 GMT",
      "version": 22
    },
    {
      "__v": 0,
      "_id": "68176a0be7010ff37c986b50",
      "code": "#include <iostream>\nusing namespace std;\n\nint main() {\n    int number;\n    cout << \"Enter an Number: \";\n    cin >> number;\n\n    double result = sqrt(number);\n\n    cout << fixed << setprecision(2);\n    cout << \"Square Root: \" << result << endl;\n\n\n    return 0;\n}",
      "learner_id": "68122d4c2c1c50f5cb914ddd",
      "problemId": "perfectly-rooted-5136456806",
      "roomId": "comp-Dx7fgmm4GB",
      "submissionId": "submission-1746364939545",
      "timestamp": "Sun, 04 May 2025 13:22:19 GMT",
      "version": 21
    },
    {
      "__v": 0,
      "_id": "68176a08e7010ff37c986b4c",
      "code": "#include <iostream>\nusing namespace std;\n\nint main() {\n    int number;\n    cout << \"Enter an Number: \";\n    cin >> number;\n\n    double result = sqrt(number);\n\n    cout << fixed << setprecision(2);\n    cout << \"Square Root: \" << result\n\n\n    return 0;\n}",
      "learner_id": "68122d4c2c1c50f5cb914ddd",
      "problemId": "perfectly-rooted-5136456806",
      "roomId": "comp-Dx7fgmm4GB",
      "submissionId": "submission-1746364936111",
      "timestamp": "Sun, 04 May 2025 13:22:16 GMT",
      "version": 20
    },
    {
      "__v": 0,
      "_id": "68176a03e7010ff37c986b48",
      "code": "#include <iostream>\nusing namespace std;\n\nint main() {\n    int number;\n    cout << \"Enter an Number: \";\n    cin >> number;\n\n    double result = sqrt(number);\n\n    cout << fixed << setprecision(2);\n    cout << \"Square Root: \"\n\n\n    return 0;\n}",
      "learner_id": "68122d4c2c1c50f5cb914ddd",
      "problemId": "perfectly-rooted-5136456806",
      "roomId": "comp-Dx7fgmm4GB",
      "submissionId": "submission-1746364931522",
      "timestamp": "Sun, 04 May 2025 13:22:11 GMT",
      "version": 19
    },
    {
      "__v": 0,
      "_id": "68176a00e7010ff37c986b44",
      "code": "#include <iostream>\nusing namespace std;\n\nint main() {\n    int number;\n    cout << \"Enter an Number: \";\n    cin >> number;\n\n    double result = sqrt(number);\n\n    cout << fixed << setprecision(2);\n    cout << \"Square Root\"\n\n\n    return 0;\n}",
      "learner_id": "68122d4c2c1c50f5cb914ddd",
      "problemId": "perfectly-rooted-5136456806",
      "roomId": "comp-Dx7fgmm4GB",
      "submissionId": "submission-1746364928780",
      "timestamp": "Sun, 04 May 2025 13:22:08 GMT",
      "version": 18
    },
    {
      "__v": 0,
      "_id": "681769fae7010ff37c986b40",
      "code": "#include <iostream>\nusing namespace std;\n\nint main() {\n    int number;\n    cout << \"Enter an Number: \";\n    cin >> number;\n\n    double result = sqrt(number);\n\n    cout << fixed << setprecision(2);\n    cout << sq\n\n\n    return 0;\n}",
      "learner_id": "68122d4c2c1c50f5cb914ddd",
      "problemId": "perfectly-rooted-5136456806",
      "roomId": "comp-Dx7fgmm4GB",
      "submissionId": "submission-1746364922839",
      "timestamp": "Sun, 04 May 2025 13:22:02 GMT",
      "version": 17
    },
    {
      "__v": 0,
      "_id": "681769f2e7010ff37c986b3a",
      "code": "#include <iostream>\nusing namespace std;\n\nint main() {\n    int number;\n    cout << \"Enter an Number: \";\n    cin >> number;\n\n    double result = sqrt(number);\n\n    cout << fixed << setprecision(2);\n    \n\n\n    return 0;\n}",
      "learner_id": "68122d4c2c1c50f5cb914ddd",
      "problemId": "perfectly-rooted-5136456806",
      "roomId": "comp-Dx7fgmm4GB",
      "submissionId": "submission-1746364914070",
      "timestamp": "Sun, 04 May 2025 13:21:54 GMT",
      "version": 16
    },
    {
      "__v": 0,
      "_id": "681769ebe7010ff37c986b36",
      "code": "#include <iostream>\nusing namespace std;\n\nint main() {\n    int number;\n    cout << \"Enter an Number: \";\n    cin >> number;\n\n    double result = sqrt(number);\n\n    cout << fixed << setprecision(2);\n\n\n    return 0;\n}",
      "learner_id": "68122d4c2c1c50f5cb914ddd",
      "problemId": "perfectly-rooted-5136456806",
      "roomId": "comp-Dx7fgmm4GB",
      "submissionId": "submission-1746364907731",
      "timestamp": "Sun, 04 May 2025 13:21:47 GMT",
      "version": 15
    },
    {
      "__v": 0,
      "_id": "681769e7e7010ff37c986b32",
      "code": "#include <iostream>\nusing namespace std;\n\nint main() {\n    int number;\n    cout << \"Enter an Number: \";\n    cin >> number;\n\n    double result = sqrt(number);\n\n    cout << fixed << setprecision(2)\n\n\n    return 0;\n}",
      "learner_id": "68122d4c2c1c50f5cb914ddd",
      "problemId": "perfectly-rooted-5136456806",
      "roomId": "comp-Dx7fgmm4GB",
      "submissionId": "submission-1746364902876",
      "timestamp": "Sun, 04 May 2025 13:21:43 GMT",
      "version": 14
    },
    {
      "__v": 0,
      "_id": "6817695f7755350287ae5730",
      "code": "#include <iostream>\nusing namespace std;\n\nint main() {\n    \n    return 0;\n}",
      "learner_id": "68122d4c2c1c50f5cb914ddd",
      "problemId": "perfectly-rooted-5136456806",
      "roomId": "comp-Dx7fgmm4GB",
      "submissionId": "submission-1746364767625",
      "timestamp": "Sun, 04 May 2025 13:19:27 GMT",
      "version": 1
    },
    {
      "__v": 0,
      "_id": "681769d3e7010ff37c986b27",
      "code": "#include <iostream>\nusing namespace std;\n\nint main() {\n    int number;\n    cout << \"Enter an Number: \";\n    cin >> number;\n\n    double result = sqrt(number);\n\n    cout <<\n\n\n    return 0;\n}",
      "learner_id": "68122d4c2c1c50f5cb914ddd",
      "problemId": "perfectly-rooted-5136456806",
      "roomId": "comp-Dx7fgmm4GB",
      "submissionId": "submission-1746364883663",
      "timestamp": "Sun, 04 May 2025 13:21:23 GMT",
      "version": 12
    },
    {
      "__v": 0,
      "_id": "681769cd7755350287ae5758",
      "code": "#include <iostream>\nusing namespace std;\n\nint main() {\n    int number;\n    cout << \"Enter an Number: \";\n    cin >> number;\n\n    double result = sqrt(number);\n\n\n    return 0;\n}",
      "learner_id": "68122d4c2c1c50f5cb914ddd",
      "problemId": "perfectly-rooted-5136456806",
      "roomId": "comp-Dx7fgmm4GB",
      "submissionId": "submission-1746364877648",
      "timestamp": "Sun, 04 May 2025 13:21:17 GMT",
      "version": 11
    },
    {
      "__v": 0,
      "_id": "681769c87755350287ae5754",
      "code": "#include <iostream>\nusing namespace std;\n\nint main() {\n    int number;\n    cout << \"Enter an Number: \";\n    cin >> number;\n\n    double result = sqrt \n\n\n    return 0;\n}",
      "learner_id": "68122d4c2c1c50f5cb914ddd",
      "problemId": "perfectly-rooted-5136456806",
      "roomId": "comp-Dx7fgmm4GB",
      "submissionId": "submission-1746364872302",
      "timestamp": "Sun, 04 May 2025 13:21:12 GMT",
      "version": 10
    },
    {
      "__v": 0,
      "_id": "681769c37755350287ae574f",
      "code": "#include <iostream>\nusing namespace std;\n\nint main() {\n    int number;\n    cout << \"Enter an Number: \";\n    cin >> number;\n\n    double result = \n\n\n    return 0;\n}",
      "learner_id": "68122d4c2c1c50f5cb914ddd",
      "problemId": "perfectly-rooted-5136456806",
      "roomId": "comp-Dx7fgmm4GB",
      "submissionId": "submission-1746364866865",
      "timestamp": "Sun, 04 May 2025 13:21:07 GMT",
      "version": 9
    },
    {
      "__v": 0,
      "_id": "681769b77755350287ae574b",
      "code": "#include <iostream>\nusing namespace std;\n\nint main() {\n    int number;\n    cout << \"Enter an Number: \";\n    cin >> number;\n\n    double sqrt \n\n\n    return 0;\n}",
      "learner_id": "68122d4c2c1c50f5cb914ddd",
      "problemId": "perfectly-rooted-5136456806",
      "roomId": "comp-Dx7fgmm4GB",
      "submissionId": "submission-1746364855363",
      "timestamp": "Sun, 04 May 2025 13:20:55 GMT",
      "version": 8
    },
    {
      "__v": 0,
      "_id": "681769b27755350287ae5747",
      "code": "#include <iostream>\nusing namespace std;\n\nint main() {\n    int number;\n    cout << \"Enter an Number: \";\n    cin >> number;\n\n    d\n\n\n    return 0;\n}",
      "learner_id": "68122d4c2c1c50f5cb914ddd",
      "problemId": "perfectly-rooted-5136456806",
      "roomId": "comp-Dx7fgmm4GB",
      "submissionId": "submission-1746364850368",
      "timestamp": "Sun, 04 May 2025 13:20:50 GMT",
      "version": 7
    },
    {
      "__v": 0,
      "_id": "681769a77755350287ae573f",
      "code": "#include <iostream>\nusing namespace std;\n\nint main() {\n    int number;\n    cout << \"Enter an Number: \";\n    cin >> number;\n\n\n    \n    return 0;\n}",
      "learner_id": "68122d4c2c1c50f5cb914ddd",
      "problemId": "perfectly-rooted-5136456806",
      "roomId": "comp-Dx7fgmm4GB",
      "submissionId": "submission-1746364838958",
      "timestamp": "Sun, 04 May 2025 13:20:39 GMT",
      "version": 6
    },
    {
      "__v": 0,
      "_id": "681769a17755350287ae573a",
      "code": "#include <iostream>\nusing namespace std;\n\nint main() {\n    int number;\n    cout << \"Enter an Number: \";\n    cin >> number;\n    return 0;\n}",
      "learner_id": "68122d4c2c1c50f5cb914ddd",
      "problemId": "perfectly-rooted-5136456806",
      "roomId": "comp-Dx7fgmm4GB",
      "submissionId": "submission-1746364833817",
      "timestamp": "Sun, 04 May 2025 13:20:33 GMT",
      "version": 5
    },
    {
      "__v": 0,
      "_id": "68176999e7010ff37c986b23",
      "code": "#include <iostream>\nusing namespace std;\n\nint main() {\n    int number;\n    cout << \"Enter an Number: \";\n    return 0;\n}",
      "learner_id": "68122d4c2c1c50f5cb914ddd",
      "problemId": "perfectly-rooted-5136456806",
      "roomId": "comp-Dx7fgmm4GB",
      "submissionId": "submission-1746364825643",
      "timestamp": "Sun, 04 May 2025 13:20:25 GMT",
      "version": 4
    },
    {
      "__v": 0,
      "_id": "68176994e7010ff37c986b1f",
      "code": "#include <iostream>\nusing namespace std;\n\nint main() {\n    int number;\n    cout << \"Enter an Number:\";\n    return 0;\n}",
      "learner_id": "68122d4c2c1c50f5cb914ddd",
      "problemId": "perfectly-rooted-5136456806",
      "roomId": "comp-Dx7fgmm4GB",
      "submissionId": "submission-1746364820541",
      "timestamp": "Sun, 04 May 2025 13:20:20 GMT",
      "version": 3
    },
    {
      "__v": 0,
      "_id": "6817697ee7010ff37c986b1b",
      "code": "#include <iostream>\nusing namespace std;\n\nint main() {\n    int number;\n    return 0;\n}",
      "learner_id": "68122d4c2c1c50f5cb914ddd",
      "problemId": "perfectly-rooted-5136456806",
      "roomId": "comp-Dx7fgmm4GB",
      "submissionId": "submission-1746364798421",
      "timestamp": "Sun, 04 May 2025 13:19:58 GMT",
      "version": 2
    }
  ],
  "success": true
}